easyaudit/__init__.py
easyaudit/admin.py
easyaudit/admin_helpers.py
easyaudit/apps.py
easyaudit/models.py
easyaudit/settings.py
easyaudit/utils.py
easyaudit/views.py
easyaudit/middleware/__init__.py
easyaudit/middleware/easyaudit.py
easyaudit/migrations/0001_initial.py
easyaudit/migrations/0002_auto_20191010_1509.py
easyaudit/migrations/0003_crudevent_change_reason.py
easyaudit/migrations/__init__.py
easyaudit/signals/__init__.py
easyaudit/signals/auth_signals.py
easyaudit/signals/model_signals.py
easyaudit/signals/request_signals.py
easyaudit/templates/admin/easyaudit/change_form_with_history_button.html
easyaudit/templates/admin/easyaudit/change_list.html
easyaudit/templates/admin/easyaudit/changes_history.html
easyaudit/templates/admin/easyaudit/purge_confirmation.html
easyaudit/templatetags/__init__.py
easyaudit/templatetags/utils_tags.py
sparing_easy_audit-1.2.dist-info/LICENSE
sparing_easy_audit-1.2.dist-info/METADATA
sparing_easy_audit-1.2.dist-info/WHEEL
sparing_easy_audit-1.2.dist-info/top_level.txt
sparing_easy_audit-1.2.dist-info/RECORD
